cluster_builder/__init__.py
cluster_builder/swarmchestrate.py
cluster_builder/config/__init__.py
cluster_builder/config/cluster.py
cluster_builder/config/postgres.py
cluster_builder/infrastructure/__init__.py
cluster_builder/infrastructure/executor.py
cluster_builder/infrastructure/templates.py
cluster_builder/templates/aws_provider.tf
cluster_builder/templates/deploy_manifest.tf
cluster_builder/templates/ha_user_data.sh.tpl
cluster_builder/templates/master_user_data.sh.tpl
cluster_builder/templates/openstack_provider.tf
cluster_builder/templates/registry_secret.tf
cluster_builder/templates/worker_user_data.sh.tpl
cluster_builder/templates/aws/main.tf
cluster_builder/templates/edge/main.tf
cluster_builder/templates/openstack/main.tf
cluster_builder/utils/__init__.py
cluster_builder/utils/hcl.py
cluster_builder/utils/logging.py
cluster_builder-0.4.4.dist-info/licenses/LICENSE
cluster_builder-0.4.4.dist-info/METADATA
cluster_builder-0.4.4.dist-info/WHEEL
cluster_builder-0.4.4.dist-info/top_level.txt
cluster_builder-0.4.4.dist-info/RECORD
