Metadata-Version: 2.4
Name: cluster-builder
Version: 0.4.4
Summary: Swarmchestrate cluster builder
Author-email: Gunjan <G.Kotak@westminster.ac.uk>, Jay <J.Deslauriers@westminster.ac.uk>
License: Apache2
License-File: LICENSE
Requires-Dist: names_generator==0.2.0
Requires-Dist: python-hcl2==7.2
Requires-Dist: lark-parser==0.12.0
Requires-Dist: python-dotenv==1.1.1
Requires-Dist: psycopg2-binary==2.9.10
Requires-Dist: yaspin==3.1.0
Requires-Dist: openstacksdk==4.8.0
Dynamic: license-file
